syndb_admin/__init__.py
syndb_admin-0.1.0.dist-info/WHEEL
syndb_admin-0.1.0.dist-info/METADATA
syndb_admin-0.1.0.dist-info/RECORD
